gwei_tracker/__init__.py
gwei_tracker/main.py
gwei_tracker-0.1.8.dist-info/METADATA
gwei_tracker-0.1.8.dist-info/WHEEL
gwei_tracker-0.1.8.dist-info/top_level.txt
gwei_tracker-0.1.8.dist-info/RECORD
